{
  "Synopsis": "Defines the subject line for an email.",
  "Description": "This function sets the subject line for an email message.",
  "Parameters": [
    {
      "Name": null,
      "Type": null,
      "Description": "",
      "Required": false,
      "Position": 0,
      "Aliases": null,
      "DefaultValue": null,
      "Globbing": false,
      "PipelineInput": null,
      "variableLength": false
    }
  ],
  "Notes": [
    null
  ],
  "CommandType": "Function",
  "Component": [
    null
  ],
  "Inputs": [
    null
  ],
  "Outputs": [
    null
  ],
  "Links": [],
  "Examples": [
    {
      "Title": "EXAMPLE 1",
      "Markdown": "",
      "Code": "EmailSubject -Subject \"Important Notification\"\r\nSets the subject line of the email to \"Important Notification\"."
    }
  ]
}