{
  "Synopsis": "Sets the owner of a file or folder.",
  "Description": "This function sets the owner of a specified file or folder to the provided owner.",
  "Parameters": [
    {
      "Name": null,
      "Type": null,
      "Description": "",
      "Required": false,
      "Position": 0,
      "Aliases": null,
      "DefaultValue": null,
      "Globbing": false,
      "PipelineInput": null,
      "variableLength": false
    }
  ],
  "Notes": [
    null
  ],
  "CommandType": "Function",
  "Component": [
    null
  ],
  "Inputs": [
    null
  ],
  "Outputs": [
    null
  ],
  "Links": [],
  "Examples": [
    {
      "Title": "EXAMPLE 1",
      "Markdown": "",
      "Code": "Set-FileOwner -Path \"C:\\Example\\File.txt\" -Owner \"DOMAIN\\User1\"\r\nDescription:\r\nSets the owner of the file \"File.txt\" to \"DOMAIN\\User1\"."
    },
    {
      "Title": "EXAMPLE 2",
      "Markdown": "",
      "Code": "Set-FileOwner -Path \"C:\\Example\\Folder\" -Owner \"DOMAIN\\User2\" -Recursive\r\nDescription:\r\nSets the owner of the folder \"Folder\" and all its contents to \"DOMAIN\\User2\" recursively."
    }
  ]
}