{
  "Synopsis": "Sets file permissions for a specified user or group on a given path.",
  "Description": "This function sets file permissions for a specified user or group on a given path. It allows you to define the type of access control, inheritance flags, and propagation flags.",
  "Parameters": [
    {
      "Name": null,
      "Type": null,
      "Description": "",
      "Required": false,
      "Position": 0,
      "Aliases": null,
      "DefaultValue": null,
      "Globbing": false,
      "PipelineInput": null,
      "variableLength": false
    }
  ],
  "Notes": [
    "File permissions are set using the Set-Acl cmdlet from the System.Security.AccessControl module."
  ],
  "CommandType": "Function",
  "Component": [
    null
  ],
  "Inputs": [
    null
  ],
  "Outputs": [
    null
  ],
  "Links": [],
  "Examples": [
    {
      "Title": "EXAMPLE 1",
      "Markdown": "",
      "Code": "Set-FilePermission -Path \"C:\\Example\\File.txt\" -Principal \"domain\\username\" -AclRightsToAssign \"Modify\"\r\nSets Modify permissions for the user 'domain\\username' on the file \"File.txt\" located at \"C:\\Example\"."
    },
    {
      "Title": "EXAMPLE 2",
      "Markdown": "",
      "Code": "Set-FilePermission -Path \"D:\\Data\" -Principal \"domain\\group\" -AclRightsToAssign \"FullControl\" -InheritedFolderPermissions @(\"ContainerInherit\")\r\nSets FullControl permissions for the group 'domain\\group' on the directory \"Data\" located at \"D:\\\" with inheritance only for subfolders."
    }
  ]
}