{
  "Synopsis": "Enables or disables user/computer section of Group Policy.",
  "Description": "Enables or disables user/computer section of Group Policy.",
  "Parameters": [
    {
      "Name": null,
      "Type": null,
      "Description": "",
      "Required": false,
      "Position": 0,
      "Aliases": null,
      "DefaultValue": null,
      "Globbing": false,
      "PipelineInput": null,
      "variableLength": false
    }
  ],
  "Notes": [
    "General notes"
  ],
  "CommandType": "Function",
  "Component": [
    null
  ],
  "Inputs": [
    null
  ],
  "Outputs": [
    null
  ],
  "Links": [],
  "Examples": [
    {
      "Title": "EXAMPLE 1",
      "Markdown": "",
      "Code": "Set-GPOZaurrStatus -Name 'TEST | Empty GPO - AD.EVOTEC.PL CrossDomain GPO' -Status AllSettingsEnabled -Verbose"
    },
    {
      "Title": "EXAMPLE 2",
      "Markdown": "",
      "Code": "Set-GPOZaurrStatus -Name 'TEST | Empty GPO - AD.EVOTEC.PL CrossDomain GPO' -DomainName ad.evotec.pl -Status AllSettingsEnabled -Verbose"
    }
  ]
}