{
  "Synopsis": "Updates a gist on GitHub.",
  "Description": "Updates a gist on GitHub.\n\nThe Git repo for this module can be found here: http://aka.ms/PowerShellForGitHub",
  "Parameters": [
    {
      "Name": null,
      "Type": null,
      "Description": "",
      "Required": false,
      "Position": 0,
      "Aliases": null,
      "DefaultValue": null,
      "Globbing": false,
      "PipelineInput": null,
      "variableLength": false
    }
  ],
  "Notes": [
    null
  ],
  "CommandType": "Filter",
  "Component": [
    null
  ],
  "Inputs": [
    "GitHub.Gist\nGitHub.GistComment\nGitHub.GistCommit\nGitHub.GistFork\nGitHub.GistSummary"
  ],
  "Outputs": [
    "GitHub.GistDetail"
  ],
  "Links": [],
  "Examples": [
    {
      "Title": "EXAMPLE 1",
      "Markdown": "",
      "Code": "Set-GitHubGist -Gist 6cad326836d38bd3a7ae -Description 'This is my newer description'\r\nUpdates the description for the specified gist."
    },
    {
      "Title": "EXAMPLE 2",
      "Markdown": "",
      "Code": "Set-GitHubGist -Gist 6cad326836d38bd3a7ae -Delete 'hello_world.rb' -Force\r\nDeletes the 'hello_world.rb' file from the specified gist without prompting for confirmation."
    },
    {
      "Title": "EXAMPLE 3",
      "Markdown": "",
      "Code": "Set-GitHubGist -Gist 6cad326836d38bd3a7ae -Delete 'hello_world.rb' -Description 'This is my newer description'\r\nDeletes the 'hello_world.rb' file from the specified gist and updates the description."
    },
    {
      "Title": "EXAMPLE 4",
      "Markdown": "",
      "Code": "Set-GitHubGist -Gist 6cad326836d38bd3a7ae -Update @{'hello_world.rb' = @{ 'fileName' = 'hello_universe.rb' }}\r\nRenames the 'hello_world.rb' file in the specified gist to be 'hello_universe.rb'."
    },
    {
      "Title": "EXAMPLE 5",
      "Markdown": "",
      "Code": "Set-GitHubGist -Gist 6cad326836d38bd3a7ae -Update @{'hello_world.rb' = @{ 'fileName' = 'hello_universe.rb' }}\r\nRenames the 'hello_world.rb' file in the specified gist to be 'hello_universe.rb'."
    }
  ]
}